{
    "package": "srp.platform.com",
    "include": [],
    "component": {
        "someip_demon": {
            "functional_groups": [
                "Startup2",
                "Platform",
                "Running",
                "SafetyMode",
                "MW"
            ],
            "parms": "",
            "reporting_mode": "AutoReporting",
            "logger": {
                "app_id": "SOME",
                "app_des": "SomeIP Demon",
                "log_level": "kInfo",
                "log_mode": "kRemote",
                "ctx": [
                    {
                        "ctx_id": "netc",
                        "log_level": "kError",
                        "ctx_des": "Default ctx for network controller"
                    }
                ]
            },
            "provide": {},
            "require": {}
        }
    }
}